LICENSE
MANIFEST.in
README.md
setup.cfg
setup.py
jjzhk/__init__.py
jjzhk/config.py
jjzhk/dataset.py
jjzhk/device.py
jjzhk/drawseg.py
jjzhk/imageutils.py
jjzhk/logger.py
jjzhk/progressbar.py
pyjjzhktools.egg-info/PKG-INFO
pyjjzhktools.egg-info/SOURCES.txt
pyjjzhktools.egg-info/dependency_links.txt
pyjjzhktools.egg-info/requires.txt
pyjjzhktools.egg-info/top_level.txt