Metadata-Version: 1.0
Name: pyjjzhktools
Version: 1.5.4
Summary: a library
Home-page: https://gitlab.com/jjzhk-group/tools/pyjjzhktools
Author: Jeff K Zhang
Author-email: jeffcobile@gmail.com
License: MIT License
Keywords: jjzhk tools
Platform: any
